thenamelisttool/__init__.py
thenamelisttool/config.py
thenamelisttool/namadapter.py
thenamelisttool/util.py
thenamelisttool/entrypoints/__init__.py
thenamelisttool/entrypoints/tnt.py
thenamelisttool/entrypoints/tntcompose.py
thenamelisttool/entrypoints/tntdiff.py
thenamelisttool/entrypoints/tntdiffpack.py
thenamelisttool/entrypoints/tntstack.py
thenamelisttool/templates/geo499c1.yaml
thenamelisttool/templates/namelist_prep_template
thenamelisttool/templates/tnt-diff-outputdir.tpl
thenamelisttool/templates/tnt-diffpack-output.tpl
thenamelisttool/templates/tnt-directive.tpl.py
thenamelisttool/templates/tnt-directive.tpl.yaml
thenamelisttool/templates/tntcompose-recipe.tpl.yaml
thenamelisttool/templates/tntstack-directive.tpl.yaml
thenamelisttool-1.3.0.dist-info/LICENSE-en.txt
thenamelisttool-1.3.0.dist-info/LICENSE.txt
thenamelisttool-1.3.0.dist-info/METADATA
thenamelisttool-1.3.0.dist-info/WHEEL
thenamelisttool-1.3.0.dist-info/entry_points.txt
thenamelisttool-1.3.0.dist-info/top_level.txt
thenamelisttool-1.3.0.dist-info/RECORD
