Metadata-Version: 2.1
Name: thenamelisttool
Version: 1.3.0
Summary: Provides command line tools useful to work with namelists or pack of namelists.
Author-email: The Vortex Team <vortex.support@meteo.fr>
License: CECILL-C
Project-URL: repository, https://github.com/meunierlf/thenamelisttool
Classifier: Development Status :: 4 - Beta
Classifier: License :: CeCILL-C Free Software License Agreement (CECILL-C)
Requires-Python: >=3.7
License-File: LICENSE-en.txt
License-File: LICENSE.txt
Requires-Dist: pyyaml
Requires-Dist: bronx
Provides-Extra: docs
Requires-Dist: sphinx ; extra == 'docs'
Provides-Extra: tests
Requires-Dist: pyyaml ; extra == 'tests'
